ggshow/__init__.py
ggshow/ggshow.py
ggshow-0.1.10.dist-info/LICENSE
ggshow-0.1.10.dist-info/METADATA
ggshow-0.1.10.dist-info/WHEEL
ggshow-0.1.10.dist-info/top_level.txt
ggshow-0.1.10.dist-info/RECORD
