Metadata-Version: 2.1
Name: ggshow
Version: 0.1.10
Summary: Draw graphs using R's ggplot2 from Python script and Jupyter notebook
Home-page: https://github.com/kota7/ggshow
Author: Kota Mori
Author-email: kmori05@gmail.com
Classifier: Development Status :: 3 - Alpha
Classifier: License :: OSI Approved :: MIT License
Classifier: Programming Language :: Python :: 3.5
Classifier: Programming Language :: Python :: 3.6
Classifier: Programming Language :: Python :: 3.7
Classifier: Programming Language :: Python :: 3.8
Classifier: Programming Language :: Python :: 3.9
License-File: LICENSE
